.gitignore
.readthedocs.yaml
LICENSE
README.md
requirements.txt
setup.py
docs/Makefile
docs/conf.py
docs/examples.rst
docs/further_reading.rst
docs/future_dev.rst
docs/index.rst
docs/make.bat
docs/monte.base_sampler.rst
docs/monte.convergence_checks.rst
docs/monte.gaussian_metropolis.rst
docs/monte.generalized_metropolis.rst
docs/monte.gibbs_sampler.rst
docs/monte.hamiltonian_mc.rst
docs/monte.importance_sampling.rst
docs/monte.metropolis_hastings.rst
docs/monte.monte_carlo_integrator.rst
docs/monte.rejection_sampling.rst
monte/__init__.py
monte/_checks.py
monte/base_sampler.py
monte/convergence_checks.py
monte/gaussian_metropolis.py
monte/generalized_metropolis.py
monte/gibbs_sampler.py
monte/hamiltonian_mc.py
monte/importance_sampling.py
monte/metropolis_hastings.py
monte/monte_carlo_integrator.py
monte/rejection_sampling.py
monte_library.egg-info/PKG-INFO
monte_library.egg-info/SOURCES.txt
monte_library.egg-info/dependency_links.txt
monte_library.egg-info/requires.txt
monte_library.egg-info/top_level.txt
tests/__init__.py
tests/test_gibbs.py
tests/test_hamiltonian_mc.py
tests/test_importance_sampling.py
tests/test_integrator.py
tests/test_metropolis.py
tests/test_metropolis_hastings.py
tests/test_rejection_sampling.py