Metadata-Version: 2.1
Name: monte-library
Version: 0.2.0
Summary: monte-library is a set of Monte Carlo methods in Python. The package is written to be flexible, clear to understand and encompass variety of Monte Carlo methods.
Home-page: https://github.com/draktr/monte-library
Author: draktr
License: MIT License
Project-URL: Documentation, https://monte-library.readthedocs.io/en/latest/
Project-URL: Issues, https://github.com/draktr/monte-library/issues
Keywords: montecarlo monte carlo,optimization,integration,sampling,mcmc,hmc,simulation,modelling
Classifier: Development Status :: 4 - Beta
Classifier: Intended Audience :: Education
Classifier: Intended Audience :: Financial and Insurance Industry
Classifier: Intended Audience :: Healthcare Industry
Classifier: Intended Audience :: Science/Research
Classifier: License :: OSI Approved :: MIT License
Classifier: Operating System :: OS Independent
Classifier: Programming Language :: Python
Classifier: Topic :: Scientific/Engineering
Classifier: Topic :: Scientific/Engineering :: Artificial Intelligence
Classifier: Topic :: Scientific/Engineering :: Bio-Informatics
Classifier: Topic :: Scientific/Engineering :: Chemistry
Classifier: Topic :: Scientific/Engineering :: Mathematics
Classifier: Topic :: Scientific/Engineering :: Physics
Requires-Python: >=3.6
License-File: LICENSE
